AUTHORS.rst
CHANGES.rst
INSTALL.rst
MANIFEST.in
README.rst
setup.cfg
setup.py
Products/__init__.py
Products.eXtremeManagement.egg-info/PKG-INFO
Products.eXtremeManagement.egg-info/SOURCES.txt
Products.eXtremeManagement.egg-info/dependency_links.txt
Products.eXtremeManagement.egg-info/entry_points.txt
Products.eXtremeManagement.egg-info/namespace_packages.txt
Products.eXtremeManagement.egg-info/not-zip-safe
Products.eXtremeManagement.egg-info/requires.txt
Products.eXtremeManagement.egg-info/top_level.txt
Products/eXtremeManagement/DEVELOPERS.txt
Products/eXtremeManagement/LICENSE.GPL
Products/eXtremeManagement/LICENSE.TXT
Products/eXtremeManagement/UPGRADES.txt
Products/eXtremeManagement/__init__.py
Products/eXtremeManagement/adapters.py
Products/eXtremeManagement/config.py
Products/eXtremeManagement/configure.zcml
Products/eXtremeManagement/credits.txt
Products/eXtremeManagement/deprecation.zcml
Products/eXtremeManagement/emails.py
Products/eXtremeManagement/localroles.py
Products/eXtremeManagement/permissions.zcml
Products/eXtremeManagement/profiles.zcml
Products/eXtremeManagement/rebuild-i18n.sh
Products/eXtremeManagement/setuphandlers.py
Products/eXtremeManagement/timing.zcml
Products/eXtremeManagement/tool.gif
Products/eXtremeManagement/utils.py
Products/eXtremeManagement/Extensions/Install.py
Products/eXtremeManagement/Extensions/__init__.py
Products/eXtremeManagement/Extensions/workflow_scripts.py
Products/eXtremeManagement/browser/__init__.py
Products/eXtremeManagement/browser/add_expanded_task.pt
Products/eXtremeManagement/browser/add_iteration.pt
Products/eXtremeManagement/browser/add_task.pt
Products/eXtremeManagement/browser/bookings.py
Products/eXtremeManagement/browser/cache.py
Products/eXtremeManagement/browser/chart.py
Products/eXtremeManagement/browser/chart_api.py
Products/eXtremeManagement/browser/close-iteration.pt
Products/eXtremeManagement/browser/closing.py
Products/eXtremeManagement/browser/configure.zcml
Products/eXtremeManagement/browser/customer.py
Products/eXtremeManagement/browser/employees.py
Products/eXtremeManagement/browser/employees_overview.pt
Products/eXtremeManagement/browser/extrememanagement.kss
Products/eXtremeManagement/browser/finished.pt
Products/eXtremeManagement/browser/gantt.py
Products/eXtremeManagement/browser/inprogress.pt
Products/eXtremeManagement/browser/interfaces.py
Products/eXtremeManagement/browser/invoicing.pt
