Metadata-Version: 1.1
Name: Products.eXtremeManagement
Version: 2.1
Summary: Project administration which supports the eXtreme Programming methodology.
Home-page: https://github.com/zestsoftware/Products.eXtremeManagement/
Author: Zest Software
Author-email: info@zestsoftware.nl
License: GPL
Keywords: project time management
Platform: UNKNOWN
Classifier: Framework :: Plone
Classifier: Framework :: Plone :: 3.3
Classifier: Framework :: Plone :: 4.0
Classifier: Framework :: Plone :: 4.1
Classifier: Framework :: Plone :: 4.2
Classifier: Framework :: Plone :: 4.3
Classifier: Framework :: Zope2
Classifier: Framework :: Zope3
Classifier: Programming Language :: Python
Classifier: Programming Language :: Python :: 2.4
Classifier: Programming Language :: Python :: 2.6
Classifier: Programming Language :: Python :: 2.7
Classifier: Topic :: Software Development :: Libraries :: Python Modules
